flood_tool/__init__.py
flood_tool/analysis.py
flood_tool/geo.py
flood_tool/live.py
flood_tool/mapping.py
flood_tool/tool.py
MSOIKK-1.0.dist-info/METADATA
MSOIKK-1.0.dist-info/WHEEL
MSOIKK-1.0.dist-info/top_level.txt
MSOIKK-1.0.dist-info/RECORD
